ml_goodput_measurement/__init__.py
ml_goodput_measurement/src/checkpoint_badput_calculator.py
ml_goodput_measurement/src/gcp_metrics.py
ml_goodput_measurement/src/goodput.py
ml_goodput_measurement/src/goodput_cache.py
ml_goodput_measurement/src/goodput_utils.py
ml_goodput_measurement/src/monitoring.py
ml_goodput_measurement/tests/checkpoint_badput_calculator_test.py
ml_goodput_measurement/tests/gcp_metrics_test.py
ml_goodput_measurement/tests/goodput_cache_test.py
ml_goodput_measurement/tests/goodput_test.py
ml_goodput_measurement/tests/monitoring_test.py
ml_goodput_measurement-0.1.36.dist-info/WHEEL
ml_goodput_measurement-0.1.36.dist-info/METADATA
ml_goodput_measurement-0.1.36.dist-info/RECORD
