Metadata-Version: 2.4
Name: ml_goodput_measurement
Version: 0.1.36
Summary: Package to monitor Goodput, Badput and other metrics of ML workloads.
Keywords: 
Author-email: Cloud TPU Team <cloud-tpu-eng@google.com>
Requires-Python: >=3.8
Classifier: Programming Language :: Python :: 3.8
Classifier: Programming Language :: Python :: 3.9
Classifier: Programming Language :: Python :: 3.10
Classifier: Programming Language :: Python :: 3.11
Requires-Dist: google-api-core>=2.24.1
Requires-Dist: google-cloud-logging>=3.5.0
Requires-Dist: google-cloud-monitoring>=2.20.0
Requires-Dist: numpy
Requires-Dist: requests
Requires-Dist: scipy
Requires-Dist: tensorboardx
Requires-Dist: urllib3
Project-URL: Bug Tracker, https://github.com/AI-Hypercomputer/ml-goodput-measurement/issues
Project-URL: Homepage, https://github.com/AI-Hypercomputer/ml-goodput-measurement
